rcsb/__init__.py
rcsb/workflow/__init__.py
rcsb/workflow/bcif/__init__.py
rcsb/workflow/bcif/task_functions.py
rcsb/workflow/chem/ChemCompFileWorkflow.py
rcsb/workflow/chem/ChemCompImageWorkflow.py
rcsb/workflow/chem/ChemCompSearchIndexWorkflow.py
rcsb/workflow/chem/__init__.py
rcsb/workflow/cli/BcifExec.py
rcsb/workflow/cli/ChemSearchIndexExec.py
rcsb/workflow/cli/ExDbExec.py
rcsb/workflow/cli/ImgExec.py
rcsb/workflow/cli/__init__.py
rcsb/workflow/targets/ProteinTargetSequenceExecutionWorkflow.py
rcsb/workflow/targets/ProteinTargetSequenceWorkflow.py
rcsb/workflow/targets/__init__.py
rcsb/workflow/wuw/BcifWorkflow.py
rcsb/workflow/wuw/ExDbWorkflow.py
rcsb/workflow/wuw/PdbCsmImageWorkflow.py
rcsb/workflow/wuw/WuwUtils.py
rcsb/workflow/wuw/__init__.py
rcsb_workflow-0.65.dist-info/METADATA
rcsb_workflow-0.65.dist-info/WHEEL
rcsb_workflow-0.65.dist-info/entry_points.txt
rcsb_workflow-0.65.dist-info/licenses/LICENSE
rcsb_workflow-0.65.dist-info/RECORD
